{
  "version": 1,
  "shortcuts": [
    {
      "label": "View Website",
      "uri": "https://bonkz.io/",
      "icon": "view"
    },
    {
      "label": "View Twitter",
      "uri": "https://twitter.com/BonkzNFT_",
      "icon": "twitter",
      "prefersExternalTarget": true
    },
    {
      "label": "View Instagram",
      "uri": "www.instagram.com/bonkz___/",
      "icon": "instagram",
      "prefersExternalTarget": true
    },
    {
      "label": "Shop Merch",
      "uri": "https://bonkzclothing.com/",
      "icon": "tip"
    },
    {
      "label": "Reveal Bonkz",
      "uri": "https://reveal.bonkz.io/",
      "icon": "mint"
    }
  ]
}
